NodeGraphQtPy/__init__.py
NodeGraphQtPy/constants.py
NodeGraphQtPy/errors.py
NodeGraphQtPy/pkg_info.py
NodeGraphQtPy/base/__init__.py
NodeGraphQtPy/base/commands.py
NodeGraphQtPy/base/factory.py
NodeGraphQtPy/base/graph.py
NodeGraphQtPy/base/menu.py
NodeGraphQtPy/base/model.py
NodeGraphQtPy/base/node.py
NodeGraphQtPy/base/port.py
NodeGraphQtPy/custom_widgets/__init__.py
NodeGraphQtPy/custom_widgets/nodes_palette.py
NodeGraphQtPy/custom_widgets/nodes_tree.py
NodeGraphQtPy/custom_widgets/properties_bin/__init__.py
NodeGraphQtPy/custom_widgets/properties_bin/custom_widget_color_picker.py
NodeGraphQtPy/custom_widgets/properties_bin/custom_widget_file_paths.py
NodeGraphQtPy/custom_widgets/properties_bin/custom_widget_slider.py
NodeGraphQtPy/custom_widgets/properties_bin/custom_widget_value_edit.py
NodeGraphQtPy/custom_widgets/properties_bin/custom_widget_vectors.py
NodeGraphQtPy/custom_widgets/properties_bin/node_property_factory.py
NodeGraphQtPy/custom_widgets/properties_bin/node_property_widgets.py
NodeGraphQtPy/custom_widgets/properties_bin/prop_widgets_abstract.py
NodeGraphQtPy/custom_widgets/properties_bin/prop_widgets_base.py
NodeGraphQtPy/nodes/__init__.py
NodeGraphQtPy/nodes/backdrop_node.py
NodeGraphQtPy/nodes/base_node.py
NodeGraphQtPy/nodes/base_node_circle.py
NodeGraphQtPy/nodes/group_node.py
NodeGraphQtPy/nodes/port_node.py
NodeGraphQtPy/qgraphics/__init__.py
NodeGraphQtPy/qgraphics/node_abstract.py
NodeGraphQtPy/qgraphics/node_backdrop.py
NodeGraphQtPy/qgraphics/node_base.py
NodeGraphQtPy/qgraphics/node_circle.py
NodeGraphQtPy/qgraphics/node_group.py
NodeGraphQtPy/qgraphics/node_overlay_disabled.py
NodeGraphQtPy/qgraphics/node_port_in.py
NodeGraphQtPy/qgraphics/node_port_out.py
NodeGraphQtPy/qgraphics/node_text_item.py
NodeGraphQtPy/qgraphics/pipe.py
NodeGraphQtPy/qgraphics/port.py
NodeGraphQtPy/qgraphics/slicer.py
NodeGraphQtPy/widgets/__init__.py
NodeGraphQtPy/widgets/actions.py
NodeGraphQtPy/widgets/dialogs.py
NodeGraphQtPy/widgets/node_graph.py
nodegraphqtpy-0.6.38.7.dist-info/METADATA
nodegraphqtpy-0.6.38.7.dist-info/WHEEL
nodegraphqtpy-0.6.38.7.dist-info/licenses/LICENSE.md
nodegraphqtpy-0.6.38.7.dist-info/RECORD
