Metadata-Version: 2.4
Name: NodeGraphQtPy
Version: 0.6.38.7
Summary: NodeGraphQtPy is a fork of NodeGraphQt using QtPy
Author: Johnny Chan (Original Author)
Author-email: Jimmy Christensen <lithorus@gmail.com>
License-File: LICENSE.md
Classifier: License :: OSI Approved :: MIT License
Classifier: Operating System :: OS Independent
Classifier: Programming Language :: Python :: 3
Requires-Python: >3.7
Requires-Dist: qtpy
